currency_normalizer/__init__.py
currency_normalizer/currencies.yaml
currency_normalizer/currency_normalizer.py
currency_normalizer-0.0.2.dist-info/METADATA
currency_normalizer-0.0.2.dist-info/WHEEL
currency_normalizer-0.0.2.dist-info/top_level.txt
currency_normalizer-0.0.2.dist-info/RECORD
